Metadata-Version: 1.0
Name: getHashData
Version: 0.3.0
Summary: Simple way to get functions or events hash or sign a message.
Home-page: https://hxzy.me
Author: th35tr0n9
Author-email: th35tr0n9@gmail.com
License: UNKNOWN
Platform: UNKNOWN
